connect_helper/__init__.py
kafka_connect_python_helper-0.0.7.dist-info/LICENSE
kafka_connect_python_helper-0.0.7.dist-info/METADATA
kafka_connect_python_helper-0.0.7.dist-info/WHEEL
kafka_connect_python_helper-0.0.7.dist-info/top_level.txt
kafka_connect_python_helper-0.0.7.dist-info/RECORD
