Metadata-Version: 2.1
Name: kafka-connect-python-helper
Version: 0.0.7
Summary: Toolset for Kafka Connect REST API
Home-page: https://github.com/MrMarshall/kafka-connect-python-helper
Author: Marcel Renders
Author-email: UNKNOWN
License: MIT
Platform: UNKNOWN
Classifier: Intended Audience :: Developers
Classifier: Programming Language :: Python :: 3
Classifier: Topic :: Software Development :: Libraries
Requires-Dist: requests (>=2.24.0)
